CHANGES.txt
MANIFEST.in
requirements-dev.txt
setup.py
interactor/__init__.py
interactor.egg-info/PKG-INFO
interactor.egg-info/SOURCES.txt
interactor.egg-info/dependency_links.txt
interactor.egg-info/top_level.txt