Metadata-Version: 1.0
Name: interactor
Version: 0.1.2
Summary: Interactor provides a common interface for performing complex user interactions.
Home-page: https://github.com/yu-liang-kono/interactor
Author: Yu Liang
Author-email: yu.liang@thekono.com
License: UNKNOWN
Platform: UNKNOWN
